ui_compiler/__init__.py
ui_compiler/cli.py
ui_compiler/common.py
ui_compiler/components.py
ui_compiler/core.py
ui_compiler/css.py
ui_compiler/js/ioinfo.js
ui_compiler/js/lw_charts.js
ui_compiler/js/multiselect.js
ui_compiler/js/select.js
ui_compiler/js/table.js
ui_compiler/js/tabs.js
ui_compiler/js/utils.js
ui_compiler/js/vega_grid.js
ui_compiler/js.py
ui_compiler/styles/base_elements.css
ui_compiler/styles/ioinfobox.css
ui_compiler/styles/kvt.css
ui_compiler/styles/layout.css
ui_compiler/styles/multiselect.css
ui_compiler/styles/pagination.css
ui_compiler/styles/search.css
ui_compiler/styles/side_nav.css
ui_compiler/styles/tabs.css
ui_compiler/styles/tooltip.css
ui_compiler/styles/top_nav.css
ui_compiler/utils.py
ui_compiler-0.1.0.dist-info/WHEEL
ui_compiler-0.1.0.dist-info/METADATA
ui_compiler-0.1.0.dist-info/RECORD
