Metadata-Version: 2.1
Name: ui-compiler
Version: 0.1.0
Summary: 
Author: Dan Kelleher
Author-email: kelleherjdan@gmail.com
Requires-Python: >=3.8,<4.0
Classifier: Programming Language :: Python :: 3
Classifier: Programming Language :: Python :: 3.10
Classifier: Programming Language :: Python :: 3.8
Classifier: Programming Language :: Python :: 3.9
Requires-Dist: cssselect (>=1.1.0,<2.0.0)
Requires-Dist: lxml (>=4.9.0,<5.0.0)
